stock_market/__init__.py
stock_market/constants.py
stock_market/dto.py
stock_market/interfaces.py
stock_market/adapters/__init__.py
stock_market/adapters/base/__init__.py
stock_market/adapters/base/response.py
stock_market/adapters/exchangerate/__init__.py
stock_market/adapters/exchangerate/dto.py
stock_market/adapters/exchangerate/params.py
stock_market/adapters/exchangerate/response.py
stock_market/adapters/exchangerate/settings.py
stock_market_adapter-0.0.3.dist-info/METADATA
stock_market_adapter-0.0.3.dist-info/WHEEL
stock_market_adapter-0.0.3.dist-info/top_level.txt
stock_market_adapter-0.0.3.dist-info/RECORD
