Metadata-Version: 2.1
Name: stock-market-adapter
Version: 0.0.3
Author: Pletnev D
Requires-Python: ~=3.7.0
Requires-Dist: requests (==2.28.2)
Requires-Dist: urllib3 (==1.26.14)
Provides-Extra: dev
Requires-Dist: pytest (~=6.2.5) ; extra == 'dev'
Requires-Dist: pytest-cov (~=2.12.1) ; extra == 'dev'
Requires-Dist: isort (~=5.10.0) ; extra == 'dev'
Requires-Dist: yapf (~=0.32.0) ; extra == 'dev'
Requires-Dist: toml (~=0.10.2) ; extra == 'dev'
Requires-Dist: flake8 (~=5.0.4) ; extra == 'dev'
Requires-Dist: Flake8-pyproject (~=1.1.0) ; extra == 'dev'
